pytest_kind/__init__.py
pytest_kind/cluster.py
pytest_kind/plugin.py
pytest_kind-22.11.1.dist-info/entry_points.txt
pytest_kind-22.11.1.dist-info/LICENSE
pytest_kind-22.11.1.dist-info/WHEEL
pytest_kind-22.11.1.dist-info/METADATA
pytest_kind-22.11.1.dist-info/RECORD
