Metadata-Version: 2.1
Name: pytest-kind
Version: 22.11.1
Summary: Kubernetes test support with KIND for pytest
Home-page: https://codeberg.org/hjacobs/pytest-kind
License: GPL-3.0+
Author: Henning Jacobs
Author-email: henning@jacobs1.de
Requires-Python: >=3.7
Classifier: Development Status :: 5 - Production/Stable
Classifier: Framework :: Pytest
Classifier: License :: OSI Approved :: GNU General Public License v3 or later (GPLv3+)
Classifier: Programming Language :: Python :: 3
Classifier: Programming Language :: Python :: 3.10
Classifier: Programming Language :: Python :: 3.7
Classifier: Programming Language :: Python :: 3.8
Classifier: Programming Language :: Python :: 3.9
Classifier: Topic :: Software Development :: Testing
Requires-Dist: pykube-ng (>=0.30)
Project-URL: Repository, https://codeberg.org/hjacobs/pytest-kind
